{
    "WorkPreset":{
        "commands": [
            {"code":"switch_1","value": true},
            {"code":"switch_2","value":true},
            {"code":"switch_3","value":false},
            {"code":"switch_4","value":false}
        ]
    },
    "HomePreset":{
        "commands": [
            {"code":"switch_1","value":true},
            {"code":"switch_2","value":false},
            {"code":"switch_3","value":true},
            {"code":"switch_4","value":false}
        ]
    },
    "Default":{
        "commands":[
            {"code":"switch_1","value":false},
            {"code":"switch_2","value":false},
            {"code":"switch_3","value":false},
            {"code":"switch_4","value":false}
        ]
    },
    "SelectedPreset":"HomePreset"
}